<?xml version="1.0" encoding="UTF-8"?>
<league>
	<sid>japan4-7</sid>
	<name>Tokai League 1</name>
	<short_name>Tokai 1</short_name>
	<symbol>flag_japan.png</symbol>
	<first_week>8</first_week>
	<week_gap>1</week_gap>
	<average_talent>4900</average_talent>
	<names_file>japan</names_file>
	<round_robins>2</round_robins>
	<break>5</break>
	<layer>4</layer>
	
	<prom_rel>
		<prom_rel_element>
			<rank_start>7</rank_start>
			<rank_end>8</rank_end>
			<dest_sid>japan5-7</dest_sid>
			<prom_rel_type>relegation</prom_rel_type>
		</prom_rel_element>
	</prom_rel>

	
	<teams>
		<team>
			<team_name>Shizuoka</team_name>
		</team>
		<team>
			<team_name>Chukyo U.</team_name>
		</team>
		<team>
			<team_name>Y. Valente</team_name>
		</team>
		<team>
			<team_name>Fujieda C.H.</team_name>
		</team>
		<team>
			<team_name>M. Kogyo</team_name>
		</team>
		<team>
			<team_name>C.B. Fujieda</team_name>
		</team>
		<team>
			<team_name>S.K. Chukyo</team_name>
		</team>
		<team>
			<team_name>Gifu</team_name>
		</team>
	</teams>
</league>