<?xml version="1.0" encoding="UTF-8"?>
<league>
  <sid>croatia3b</sid>
  <name>Treća Hrvatska Liga Istok</name>
  <short_name>Treća HNL I</short_name>
  <symbol>flag_croatia.png</symbol>
  <first_week>5</first_week>
  <week_gap>1</week_gap>
  <break_in length="10">24</break_in>
  <average_talent>6000</average_talent>
  <names_file>serbia</names_file>
  <yellow_red>5</yellow_red>
  <layer>3</layer>

  <prom_rel>
    <prom_rel_element>
      <rank_start>1</rank_start>
      <rank_end>1</rank_end>
      <dest_sid>croatia2</dest_sid>
      <prom_rel_type>promotion</prom_rel_type>
    </prom_rel_element>
  </prom_rel>

  <teams>
    <team>
      <team_name>Belišće</team_name>
    </team>
    <team>
      <team_name>Bjelovar</team_name>
    </team>
    <team>
      <team_name>C. Đakovo</team_name>
    </team>
    <team>
      <team_name>N. Đakovo</team_name>
    </team>
    <team>
      <team_name>G. V. Osijek</team_name>
    </team>
    <team>
      <team_name>G. Županja</team_name>
    </team>
    <team>
      <team_name>Koprivnica</team_name>
    </team>
    <team>
      <team_name>Križevci</team_name>
    </team>
    <team>
      <team_name>M. Slavonski Brod</team_name>
    </team>
    <team>
      <team_name>M. Cernik</team_name>
    </team>
    <team>
      <team_name>M. Prelog</team_name>
    </team>
    <team>
      <team_name>N. Našice</team_name>
    </team>
    <team>
      <team_name>Nedelišće</team_name>
    </team>
    <team>
      <team_name>O. Osijek</team_name>
    </team>
    <team>
      <team_name>S. Pleternica</team_name>
    </team>
    <team>
      <team_name>Virovitica</team_name>
    </team>
    <team>
      <team_name>Visnjevac</team_name>
    </team>
    <team>
      <team_name>Vukovar</team_name>
    </team>
  </teams>
</league>