<names>
	<first_name>Adam</first_name>
	<first_name>Adrian</first_name>
	<first_name>Albin</first_name>
	<first_name>Alex</first_name>
	<first_name>Alexander</first_name>
	<first_name>Alfons</first_name>
	<first_name>Alfred</first_name>
	<first_name>Ali</first_name>
	<first_name>Alvin</first_name>
	<first_name>André</first_name>
	<first_name>Andreas</first_name>
	<first_name>Anton</first_name>
	<first_name>Arvid</first_name>
	<first_name>August</first_name>
	<first_name>Axel</first_name>
	<first_name>Benjamin</first_name>
	<first_name>Carl</first_name>
	<first_name>Casper</first_name>
	<first_name>Charlie</first_name>
	<first_name>Christoffer</first_name>
	<first_name>Daniel</first_name>
	<first_name>David</first_name>
	<first_name>Dennis</first_name>
	<first_name>Eddie</first_name>
	<first_name>Edvin</first_name>
	<first_name>Edwin</first_name>
	<first_name>Elias</first_name>
	<first_name>Elis</first_name>
	<first_name>Elliot</first_name>
	<first_name>Emil</first_name>
	<first_name>Eric</first_name>
	<first_name>Erik</first_name>
	<first_name>Fabian</first_name>
	<first_name>Felix</first_name>
	<first_name>Filip</first_name>
	<first_name>Fredrik</first_name>
	<first_name>Gabriel</first_name>
	<first_name>Gustaf</first_name>
	<first_name>Gustav</first_name>
	<first_name>Hampus</first_name>
	<first_name>Hannes</first_name>
	<first_name>Henrik</first_name>
	<first_name>Herman</first_name>
	<first_name>Hjalmar</first_name>
	<first_name>Hugo</first_name>
	<first_name>Isac</first_name>
	<first_name>Isak</first_name>
	<first_name>Ivar</first_name>
	<first_name>Jack</first_name>
	<first_name>Jacob</first_name>
	<first_name>Jakob</first_name>
	<first_name>Jesper</first_name>
	<first_name>Joakim</first_name>
	<first_name>Joel</first_name>
	<first_name>Johan</first_name>
	<first_name>Johannes</first_name>
	<first_name>John</first_name>
	<first_name>Jonas</first_name>
	<first_name>Jonatan</first_name>
	<first_name>Jonathan</first_name>
	<first_name>Josef</first_name>
	<first_name>Kalle</first_name>
	<first_name>Karl</first_name>
	<first_name>Kasper</first_name>
	<first_name>Kevin</first_name>
	<first_name>Kim</first_name>
	<first_name>Leo</first_name>
	<first_name>Leon</first_name>
	<first_name>Liam</first_name>
	<first_name>Linus</first_name>
	<first_name>Loke</first_name>
	<first_name>Love</first_name>
	<first_name>Lucas</first_name>
	<first_name>Ludvig</first_name>
	<first_name>Ludwig</first_name>
	<first_name>Lukas</first_name>
	<first_name>Måns</first_name>
	<first_name>Malte</first_name>
	<first_name>Marcus</first_name>
	<first_name>Markus</first_name>
	<first_name>Martin</first_name>
	<first_name>Mattias</first_name>
	<first_name>Max</first_name>
	<first_name>Maximilian</first_name>
	<first_name>Melker</first_name>
	<first_name>Melvin</first_name>
	<first_name>Neo</first_name>
	<first_name>Nils</first_name>
	<first_name>Noah</first_name>
	<first_name>Noel</first_name>
	<first_name>Oliver</first_name>
	<first_name>Olle</first_name>
	<first_name>Olof</first_name>
	<first_name>Oscar</first_name>
	<first_name>Oskar</first_name>
	<first_name>Otto</first_name>
	<first_name>Philip</first_name>
	<first_name>Pontus</first_name>
	<first_name>Rasmus</first_name>
	<first_name>Robin</first_name>
	<first_name>Samuel</first_name>
	<first_name>Sebastian</first_name>
	<first_name>Simon</first_name>
	<first_name>Sixten</first_name>
	<first_name>Svante</first_name>
	<first_name>Theo</first_name>
	<first_name>Theodor</first_name>
	<first_name>Tim</first_name>
	<first_name>Tobias</first_name>
	<first_name>Victor</first_name>
	<first_name>Viggo</first_name>
	<first_name>Viktor</first_name>
	<first_name>Vilgot</first_name>
	<first_name>Ville</first_name>
	<first_name>Vincent</first_name>
	<first_name>Wilhelm</first_name>
	<first_name>William</first_name>
	<first_name>Wilmer</first_name>


	<last_name>Åberg</last_name>
	<last_name>Öberg</last_name>
	<last_name>Abrahamsson</last_name>
	<last_name>Adam</last_name>
	<last_name>Adrian</last_name>
	<last_name>Åkesson</last_name>
	<last_name>Albin</last_name>
	<last_name>Alex</last_name>
	<last_name>Alexander</last_name>
	<last_name>Alfons</last_name>
	<last_name>Alfred</last_name>
	<last_name>Ali</last_name>
	<last_name>Alvin</last_name>
	<last_name>Andersson</last_name>
	<last_name>André</last_name>
	<last_name>Andreas</last_name>
	<last_name>Andreasson</last_name>
	<last_name>Anton</last_name>
	<last_name>Arvid</last_name>
	<last_name>Arvidsson</last_name>
	<last_name>Åström</last_name>
	<last_name>August</last_name>
	<last_name>Axel</last_name>
	<last_name>Axelsson</last_name>
	<last_name>Bengtsson</last_name>
	<last_name>Benjamin</last_name>
	<last_name>Berg</last_name>
	<last_name>Berggren</last_name>
	<last_name>Berglund</last_name>
	<last_name>Bergman</last_name>
	<last_name>Bergqvist</last_name>
	<last_name>Bergström</last_name>
	<last_name>Björk</last_name>
	<last_name>Björklund</last_name>
	<last_name>Blom</last_name>
	<last_name>Blomqvist</last_name>
	<last_name>Carl</last_name>
	<last_name>Carlsson</last_name>
	<last_name>Casper</last_name>
	<last_name>Charlie</last_name>
	<last_name>Christoffer</last_name>
	<last_name>Dahl</last_name>
	<last_name>Dahlberg</last_name>
	<last_name>Daniel</last_name>
	<last_name>Danielsson</last_name>
	<last_name>David</last_name>
	<last_name>Dennis</last_name>
	<last_name>Eddie</last_name>
	<last_name>Edvin</last_name>
	<last_name>Edwin</last_name>
	<last_name>Ek</last_name>
	<last_name>Eklund</last_name>
	<last_name>Ekström</last_name>
	<last_name>Elias</last_name>
	<last_name>Eliasson</last_name>
	<last_name>Elis</last_name>
	<last_name>Elliot</last_name>
	<last_name>Emil</last_name>
	<last_name>Engström</last_name>
	<last_name>Eric</last_name>
	<last_name>Erik</last_name>
	<last_name>Eriksson</last_name>
	<last_name>Fabian</last_name>
	<last_name>Felix</last_name>
	<last_name>Filip</last_name>
	<last_name>Forsberg</last_name>
	<last_name>Fransson</last_name>
	<last_name>Fredrik</last_name>
	<last_name>Fredriksson</last_name>
	<last_name>Gabriel</last_name>
	<last_name>Göransson</last_name>
	<last_name>Gunnarsson</last_name>
	<last_name>Gustaf</last_name>
	<last_name>Gustafsson</last_name>
	<last_name>Gustav</last_name>
	<last_name>Gustavsson</last_name>
	<last_name>Håkansson</last_name>
	<last_name>Hampus</last_name>
	<last_name>Hannes</last_name>
	<last_name>Hansson</last_name>
	<last_name>Hedlund</last_name>
	<last_name>Hellström</last_name>
	<last_name>Henrik</last_name>
	<last_name>Henriksson</last_name>
	<last_name>Herman</last_name>
	<last_name>Hermansson</last_name>
	<last_name>Hjalmar</last_name>
	<last_name>Holm</last_name>
	<last_name>Holmberg</last_name>
	<last_name>Holmgren</last_name>
	<last_name>Hugo</last_name>
	<last_name>Isac</last_name>
	<last_name>Isak</last_name>
	<last_name>Isaksson</last_name>
	<last_name>Ivar</last_name>
	<last_name>Ivarsson</last_name>
	<last_name>Jack</last_name>
	<last_name>Jacob</last_name>
	<last_name>Jakob</last_name>
	<last_name>Jakobsson</last_name>
	<last_name>Jansson</last_name>
	<last_name>Jönsson</last_name>
	<last_name>Jesper</last_name>
	<last_name>Joakim</last_name>
	<last_name>Joel</last_name>
	<last_name>Johan</last_name>
	<last_name>Johannes</last_name>
	<last_name>Johansson</last_name>
	<last_name>John</last_name>
	<last_name>Johnsson</last_name>
	<last_name>Jonas</last_name>
	<last_name>Jonasson</last_name>
	<last_name>Jonatan</last_name>
	<last_name>Jonathan</last_name>
	<last_name>Jonsson</last_name>
	<last_name>Josef</last_name>
	<last_name>Kalle</last_name>
	<last_name>Karl</last_name>
	<last_name>Karlsson</last_name>
	<last_name>Kasper</last_name>
	<last_name>Kevin</last_name>
	<last_name>Kim</last_name>
	<last_name>Larsson</last_name>
	<last_name>Löfgren</last_name>
	<last_name>Leo</last_name>
	<last_name>Leon</last_name>
	<last_name>Liam</last_name>
	<last_name>Lind</last_name>
	<last_name>Lindberg</last_name>
	<last_name>Lindgren</last_name>
	<last_name>Lindholm</last_name>
	<last_name>Lindqvist</last_name>
	<last_name>Lindström</last_name>
	<last_name>Linus</last_name>
	<last_name>Loke</last_name>
	<last_name>Love</last_name>
	<last_name>Lucas</last_name>
	<last_name>Ludvig</last_name>
	<last_name>Ludwig</last_name>
	<last_name>Lukas</last_name>
	<last_name>Lund</last_name>
	<last_name>Lundberg</last_name>
	<last_name>Lundgren</last_name>
	<last_name>Lundin</last_name>
	<last_name>Lundqvist</last_name>
	<last_name>Lundström</last_name>
	<last_name>Magnusson</last_name>
	<last_name>Måns</last_name>
	<last_name>Månsson</last_name>
	<last_name>Mårtensson</last_name>
	<last_name>Malte</last_name>
	<last_name>Marcus</last_name>
	<last_name>Markus</last_name>
	<last_name>Martin</last_name>
	<last_name>Martinsson</last_name>
	<last_name>Mattias</last_name>
	<last_name>Mattsson</last_name>
	<last_name>Max</last_name>
	<last_name>Maximilian</last_name>
	<last_name>Melker</last_name>
	<last_name>Melvin</last_name>
	<last_name>Neo</last_name>
	<last_name>Nils</last_name>
	<last_name>Nilsson</last_name>
	<last_name>Noah</last_name>
	<last_name>Noel</last_name>
	<last_name>Norberg</last_name>
	<last_name>Nordin</last_name>
	<last_name>Nordström</last_name>
	<last_name>Nyberg</last_name>
	<last_name>Nyman</last_name>
	<last_name>Nyström</last_name>
	<last_name>Oliver</last_name>
	<last_name>Olle</last_name>
	<last_name>Olof</last_name>
	<last_name>Olofsson</last_name>
	<last_name>Olsson</last_name>
	<last_name>Oscar</last_name>
	<last_name>Oskar</last_name>
	<last_name>Otto</last_name>
	<last_name>Persson</last_name>
	<last_name>Petersson</last_name>
	<last_name>Pettersson</last_name>
	<last_name>Philip</last_name>
	<last_name>Pontus</last_name>
	<last_name>Rasmus</last_name>
	<last_name>Robin</last_name>
	<last_name>Samuel</last_name>
	<last_name>Samuelsson</last_name>
	<last_name>Sandberg</last_name>
	<last_name>Sandström</last_name>
	<last_name>Söderberg</last_name>
	<last_name>Söderström</last_name>
	<last_name>Sebastian</last_name>
	<last_name>Simon</last_name>
	<last_name>Sixten</last_name>
	<last_name>Sjöberg</last_name>
	<last_name>Sjögren</last_name>
	<last_name>Ström</last_name>
	<last_name>Strömberg</last_name>
	<last_name>Sundberg</last_name>
	<last_name>Sundström</last_name>
	<last_name>Svante</last_name>
	<last_name>Svensson</last_name>
	<last_name>Theo</last_name>
	<last_name>Theodor</last_name>
	<last_name>Tim</last_name>
	<last_name>Tobias</last_name>
	<last_name>Victor</last_name>
	<last_name>Viggo</last_name>
	<last_name>Viktor</last_name>
	<last_name>Vilgot</last_name>
	<last_name>Ville</last_name>
	<last_name>Vincent</last_name>
	<last_name>Wallin</last_name>
	<last_name>Wilhelm</last_name>
	<last_name>William</last_name>
	<last_name>Wilmer</last_name>
</names>
