<names>
	<first_name>Akhrik</first_name>
	<first_name>Aleksei</first_name>
	<first_name>Anatoliy</first_name>
	<first_name>Andrij</first_name>
	<first_name>Andriy</first_name>
	<first_name>Anton</first_name>
	<first_name>Arimas</first_name>
	<first_name>Armen</first_name>
	<first_name>Artem</first_name>
	<first_name>Artur</first_name>
	<first_name>Bohdan</first_name>
	<first_name>Borys</first_name>
	<first_name>Dema</first_name>
	<first_name>Denis</first_name>
	<first_name>Denys</first_name>
	<first_name>Dmytriy</first_name>
	<first_name>Dmytro</first_name>
	<first_name>Eduard</first_name>
	<first_name>Evgen</first_name>
	<first_name>Evgueni</first_name>
	<first_name>Evhen</first_name>
	<first_name>Gennadiy</first_name>
	<first_name>Gennady</first_name>
	<first_name>Georgi</first_name>
	<first_name>Hennadiy</first_name>
	<first_name>Hennady</first_name>
	<first_name>Hryhoriy</first_name>
	<first_name>Igor</first_name>
	<first_name>Ihor</first_name>
	<first_name>Ilia</first_name>
	<first_name>Illya</first_name>
	<first_name>Ilya</first_name>
	<first_name>Irfan</first_name>
	<first_name>Ivan</first_name>
	<first_name>Jevgeni</first_name>
	<first_name>Konstantyn</first_name>
	<first_name>Konstanyn</first_name>
	<first_name>Kostantyn</first_name>
	<first_name>Kyrylo</first_name>
	<first_name>Leonid</first_name>
	<first_name>Lybomyr</first_name>
	<first_name>Maksim</first_name>
	<first_name>Maksym</first_name>
	<first_name>Marko</first_name>
	<first_name>Maryan</first_name>
	<first_name>Matviy</first_name>
	<first_name>Maxym</first_name>
	<first_name>Mykhaylo</first_name>
	<first_name>Mykola</first_name>
	<first_name>Myroslav</first_name>
	<first_name>Nykita</first_name>
	<first_name>Oleg</first_name>
	<first_name>Oleh</first_name>
	<first_name>Oleksandr</first_name>
	<first_name>Oleksiy</first_name>
	<first_name>Pavel</first_name>
	<first_name>Pavlo</first_name>
	<first_name>Petro</first_name>
	<first_name>Rinar</first_name>
	<first_name>Rizvan</first_name>
	<first_name>Roman</first_name>
	<first_name>Rostyslav</first_name>
	<first_name>Ruslan</first_name>
	<first_name>Rustam</first_name>
	<first_name>Semen</first_name>
	<first_name>Sergei</first_name>
	<first_name>Sergey</first_name>
	<first_name>Serhij</first_name>
	<first_name>Serhiy</first_name>
	<first_name>Stanyslav</first_name>
	<first_name>Stefan</first_name>
	<first_name>Stepan</first_name>
	<first_name>Svyatoslav</first_name>
	<first_name>Taras</first_name>
	<first_name>Timerlan</first_name>
	<first_name>Vadym</first_name>
	<first_name>Valentyn</first_name>
	<first_name>Valeriy</first_name>
	<first_name>Vasyl</first_name>
	<first_name>Vasyliy</first_name>
	<first_name>Viacheslav</first_name>
	<first_name>Viktor</first_name>
	<first_name>Vitali</first_name>
	<first_name>Vladimir</first_name>
	<first_name>Vladyslav</first_name>
	<first_name>Volodymyr</first_name>
	<first_name>Vsevolod</first_name>
	<first_name>Vyacheslav</first_name>
	<first_name>Yarema</first_name>
	<first_name>Yaroslav</first_name>
	<first_name>Yegor</first_name>
	<first_name>Yevhen</first_name>
	<first_name>Yevheniy</first_name>
	<first_name>Yevhenniy</first_name>
	<first_name>Yozhef</first_name>
	<first_name>Yuri</first_name>
	<first_name>Yury</first_name>



	<last_name>Ablitarov</last_name>
	<last_name>Akopyan</last_name>
	<last_name>Aliyev</last_name>
	<last_name>Altman</last_name>
	<last_name>Ametov</last_name>
	<last_name>Andriyenko</last_name>
	<last_name>Antipov</last_name>
	<last_name>Antonov</last_name>
	<last_name>Artemenko</last_name>
	<last_name>Artiukh</last_name>
	<last_name>Arzhanov</last_name>
	<last_name>Ataev</last_name>
	<last_name>Atelkin</last_name>
	<last_name>Babenko</last_name>
	<last_name>Babych</last_name>
	<last_name>Bakharev</last_name>
	<last_name>Bal</last_name>
	<last_name>Balabanov</last_name>
	<last_name>Baltacha</last_name>
	<last_name>Bandrivskyy</last_name>
	<last_name>Bandura</last_name>
	<last_name>Bannikov</last_name>
	<last_name>Baranets</last_name>
	<last_name>Baranov</last_name>
	<last_name>Barylko</last_name>
	<last_name>Baryshnikov</last_name>
	<last_name>Bashakov</last_name>
	<last_name>Bazhan</last_name>
	<last_name>Bazilevich</last_name>
	<last_name>Belanov</last_name>
	<last_name>Bendovskyi</last_name>
	<last_name>Benio</last_name>
	<last_name>Berezhnoy</last_name>
	<last_name>Berezovchuk</last_name>
	<last_name>Berezovski</last_name>
	<last_name>Bessonov</last_name>
	<last_name>Bezhenar</last_name>
	<last_name>Bezotosnyy</last_name>
	<last_name>Biba</last_name>
	<last_name>Bidlovskyi</last_name>
	<last_name>Bidnenko</last_name>
	<last_name>Biletskyi</last_name>
	<last_name>Bilozir</last_name>
	<last_name>Bilyy</last_name>
	<last_name>Blavatskiy</last_name>
	<last_name>Blokhin</last_name>
	<last_name>Blyzniuk</last_name>
	<last_name>Bobal</last_name>
	<last_name>Bohatenko</last_name>
	<last_name>Bohush</last_name>
	<last_name>Boiko</last_name>
	<last_name>Bondarenko</last_name>
	<last_name>Borovyk</last_name>
	<last_name>Boychenko</last_name>
	<last_name>Boyko</last_name>
	<last_name>Braila</last_name>
	<last_name>Bredun</last_name>
	<last_name>Brovkin</last_name>
	<last_name>Bundash</last_name>
	<last_name>Buryak</last_name>
	<last_name>Buryi</last_name>
	<last_name>Butenko</last_name>
	<last_name>Byelik</last_name>
	<last_name>Byshovets</last_name>
	<last_name>Chanov</last_name>
	<last_name>Chapko</last_name>
	<last_name>Cheberyachko</last_name>
	<last_name>Chebotariv</last_name>
	<last_name>Checher</last_name>
	<last_name>Chepurnenko</last_name>
	<last_name>Cherednyk</last_name>
	<last_name>Cherniak</last_name>
	<last_name>Chesnakov</last_name>
	<last_name>Chizhevskiy</last_name>
	<last_name>Chopik</last_name>
	<last_name>Chopyk</last_name>
	<last_name>Chuchman</last_name>
	<last_name>Chuvayev</last_name>
	<last_name>Chychykоv</last_name>
	<last_name>Chygrynskiy</last_name>
	<last_name>Chyzhov</last_name>
	<last_name>Dankiv</last_name>
	<last_name>Danylovskyi</last_name>
	<last_name>Degtyaryov</last_name>
	<last_name>Demchenko</last_name>
	<last_name>Demyanenko</last_name>
	<last_name>Deonas</last_name>
	<last_name>Dević</last_name>
	<last_name>Didenko</last_name>
	<last_name>Dikan</last_name>
	<last_name>Diryavka</last_name>
	<last_name>Dmitrulin</last_name>
	<last_name>Dolhansky</last_name>
	<last_name>Donets</last_name>
	<last_name>Dopilka</last_name>
	<last_name>Dotsenko</last_name>
	<last_name>Dudnyk</last_name>
	<last_name>Dyachuk</last_name>
	<last_name>Esin</last_name>
	<last_name>Fedetskyy</last_name>
	<last_name>Fedorchuk</last_name>
	<last_name>Fedoriv</last_name>
	<last_name>Fedorov</last_name>
	<last_name>Fedosenko</last_name>
	<last_name>Fenin</last_name>
	<last_name>Ferents</last_name>
	<last_name>Feschuk</last_name>
	<last_name>Fomenko</last_name>
	<last_name>Fomin</last_name>
	<last_name>Forkash</last_name>
	<last_name>Furta</last_name>
	<last_name>Gabito</last_name>
	<last_name>Galyuza</last_name>
	<last_name>Gluschenko</last_name>
	<last_name>Golaydo</last_name>
	<last_name>Gorodov</last_name>
	<last_name>Gorshkov</last_name>
	<last_name>Goryainov</last_name>
	<last_name>Goryslavets</last_name>
	<last_name>Grachyov</last_name>
	<last_name>Grinchenko</last_name>
	<last_name>Gryshyn</last_name>
	<last_name>Grytsay</last_name>
	<last_name>Gulordava</last_name>
	<last_name>Habovda</last_name>
	<last_name>Hai</last_name>
	<last_name>Haidash</last_name>
	<last_name>Halchuk</last_name>
	<last_name>Havrushiv</last_name>
	<last_name>Hay</last_name>
	<last_name>Herasymyuk</last_name>
	<last_name>Hetsko</last_name>
	<last_name>Hilaziv</last_name>
	<last_name>Hladky</last_name>
	<last_name>Hluschenko</last_name>
	<last_name>Hodzyur</last_name>
	<last_name>Holodyuk</last_name>
	<last_name>Holopyorov</last_name>
	<last_name>Holovaniv</last_name>
	<last_name>Holovko</last_name>
	<last_name>Homenyuk</last_name>
	<last_name>Homin</last_name>
	<last_name>Hordienko</last_name>
	<last_name>Hordya</last_name>
	<last_name>Horetskyy</last_name>
	<last_name>Hramm</last_name>
	<last_name>Hranovsky</last_name>
	<last_name>Hrinchenko</last_name>
	<last_name>Hromiv</last_name>
	<last_name>Hryschenko</last_name>
	<last_name>Hryshko</last_name>
	<last_name>Hryshyn</last_name>
	<last_name>Hryszczenko</last_name>
	<last_name>Hrytsuk</last_name>
	<last_name>Humenyuk</last_name>
	<last_name>Hunchak</last_name>
	<last_name>Hurskyi</last_name>
	<last_name>Huseinov</last_name>
	<last_name>Husin</last_name>
	<last_name>Husyev</last_name>
	<last_name>Iachtchouk</last_name>
	<last_name>Iakovenko</last_name>
	<last_name>Ianchuk</last_name>
	<last_name>Illkiv</last_name>
	<last_name>Ilnytskyy</last_name>
	<last_name>Ischenko</last_name>
	<last_name>Ishmakov</last_name>
	<last_name>Istomin</last_name>
	<last_name>Ivanko</last_name>
	<last_name>Ivanov</last_name>
	<last_name>Ivaschenko</last_name>
	<last_name>Kachorenko</last_name>
	<last_name>Kalitvintsev</last_name>
	<last_name>Kalynychenko</last_name>
	<last_name>Kameniuka</last_name>
	<last_name>Kanchelskis</last_name>
	<last_name>Kandaurov</last_name>
	<last_name>Kanibolotskiy</last_name>
	<last_name>Kaplichny</last_name>
	<last_name>Karabin</last_name>
	<last_name>Karakevych</last_name>
	<last_name>Karamushka</last_name>
	<last_name>Kardash</last_name>
	<last_name>Karnoza</last_name>
	<last_name>Karpenko</last_name>
	<last_name>Karpov</last_name>
	<last_name>Kasyanov</last_name>
	<last_name>Kavatsiv</last_name>
	<last_name>Kaverin</last_name>
	<last_name>Kernozenko</last_name>
	<last_name>Kharchenko</last_name>
	<last_name>Khmelnitsky</last_name>
	<last_name>Khovbosha</last_name>
	<last_name>Khramtsov</last_name>
	<last_name>Khudobyak</last_name>
	<last_name>Khudzhamov</last_name>
	<last_name>Khudzik</last_name>
	<last_name>Kikot</last_name>
	<last_name>Kirlyk</last_name>
	<last_name>Kitsuta</last_name>
	<last_name>Kobin</last_name>
	<last_name>Kohut</last_name>
	<last_name>Kolotov</last_name>
	<last_name>Komarnitskyy</last_name>
	<last_name>Komarytskyi</last_name>
	<last_name>Kondratiuk</last_name>
	<last_name>Kondratyuk</last_name>
	<last_name>Koniushenko</last_name>
	<last_name>Konjkov</last_name>
	<last_name>Konoplianka</last_name>
	<last_name>Konovalov</last_name>
	<last_name>Kopil</last_name>
	<last_name>Kopolovets</last_name>
	<last_name>Kormiltsev</last_name>
	<last_name>Kornev</last_name>
	<last_name>Korobka</last_name>
	<last_name>Korobochka</last_name>
	<last_name>Korotetsky</last_name>
	<last_name>Korotetskyy</last_name>
	<last_name>Kortunyak</last_name>
	<last_name>Kosovsky</last_name>
	<last_name>Kostiuk</last_name>
	<last_name>Kostyshyn</last_name>
	<last_name>Kosyrin</last_name>
	<last_name>Koteliukh</last_name>
	<last_name>Kotenko</last_name>
	<last_name>Kots</last_name>
	<last_name>Koval</last_name>
	<last_name>Kovalchuk</last_name>
	<last_name>Kovalenko</last_name>
	<last_name>Kovalets</last_name>
	<last_name>Kovpak</last_name>
	<last_name>Kozachenko</last_name>
	<last_name>Kozak</last_name>
	<last_name>Kozban</last_name>
	<last_name>Kozhanov</last_name>
	<last_name>Kozinkevich</last_name>
	<last_name>Kozoriz</last_name>
	<last_name>Krakovsky</last_name>
	<last_name>Krasnoperov</last_name>
	<last_name>Kravchenko</last_name>
	<last_name>Kravets</last_name>
	<last_name>Kretov</last_name>
	<last_name>Kruglyak</last_name>
	<last_name>Kryvosheenko</last_name>
	<last_name>Kryvoshyyiv</last_name>
	<last_name>Kryvtsov</last_name>
	<last_name>Ksyonz</last_name>
	<last_name>Kucher</last_name>
	<last_name>Kucherenko</last_name>
	<last_name>Kucherevsky</last_name>
	<last_name>Kucherevskyy</last_name>
	<last_name>Kuchis</last_name>
	<last_name>Kulakov</last_name>
	<last_name>Kulchytsky</last_name>
	<last_name>Kurylov</last_name>
	<last_name>Kusliy</last_name>
	<last_name>Kutas</last_name>
	<last_name>Kutepov</last_name>
	<last_name>Kutsyaba</last_name>
	<last_name>Kuznetsov</last_name>
	<last_name>Kuzyk</last_name>
	<last_name>Kyrylov</last_name>
	<last_name>Lazarovich</last_name>
	<last_name>Lebedynets</last_name>
	<last_name>Leonenko</last_name>
	<last_name>Leonidov</last_name>
	<last_name>Leshchuk</last_name>
	<last_name>Levchenko</last_name>
	<last_name>Levitsky</last_name>
	<last_name>Levyga</last_name>
	<last_name>Litovchenko</last_name>
	<last_name>Liubarskyi</last_name>
	<last_name>Liuty</last_name>
	<last_name>Ljashko</last_name>
	<last_name>Loban</last_name>
	<last_name>Lobanovsky</last_name>
	<last_name>Loktionov</last_name>
	<last_name>Lugachyov</last_name>
	<last_name>Lutsenko</last_name>
	<last_name>Lutsyk</last_name>
	<last_name>Luzhny</last_name>
	<last_name>Lyopa</last_name>
	<last_name>Lysenko</last_name>
	<last_name>Lysytsky</last_name>
	<last_name>Lytovchenko</last_name>
	<last_name>Makarenko</last_name>
	<last_name>Makhnovskyy</last_name>
	<last_name>Maksymov</last_name>
	<last_name>Malygin</last_name>
	<last_name>Mamaev</last_name>
	<last_name>Mandzyuk</last_name>
	<last_name>Martynyuk</last_name>
	<last_name>Martyschuk</last_name>
	<last_name>Marushchak</last_name>
	<last_name>Matiukhin</last_name>
	<last_name>Matkevych</last_name>
	<last_name>Matvienko</last_name>
	<last_name>Matviyiv</last_name>
	<last_name>Matyazh</last_name>
	<last_name>Maximov</last_name>
	<last_name>Mazurenko</last_name>
	<last_name>Mazyar</last_name>
	<last_name>Medvediev</last_name>
	<last_name>Melaschenko</last_name>
	<last_name>Melnychenko</last_name>
	<last_name>Melnyk</last_name>
	<last_name>Mikhailichenko</last_name>
	<last_name>Mikhalik</last_name>
	<last_name>Milevskiy</last_name>
	<last_name>Milko</last_name>
	<last_name>Miroshnychenko</last_name>
	<last_name>Momot</last_name>
	<last_name>Monakhov</last_name>
	<last_name>Monaryov</last_name>
	<last_name>Morozov</last_name>
	<last_name>Morozyuk</last_name>
	<last_name>Mostovyy</last_name>
	<last_name>Muntyan</last_name>
	<last_name>Mykhailenko</last_name>
	<last_name>Mykulyak</last_name>
	<last_name>Mysiaylo</last_name>
	<last_name>Nad</last_name>
	<last_name>Nahirnyi</last_name>
	<last_name>Nazarenko</last_name>
	<last_name>Nazarov</last_name>
	<last_name>Nelin</last_name>
	<last_name>Nepohodov</last_name>
	<last_name>Nesmachniy</last_name>
	<last_name>Nevmyvaka</last_name>
	<last_name>Nikiforov</last_name>
	<last_name>Novak</last_name>
	<last_name>Novosyletskyy</last_name>
	<last_name>Oberemko</last_name>
	<last_name>Obrevko</last_name>
	<last_name>Odolskyy</last_name>
	<last_name>Olefir</last_name>
	<last_name>Olijnyk</last_name>
	<last_name>Oliynyk</last_name>
	<last_name>Omelchenko</last_name>
	<last_name>Onischenko</last_name>
	<last_name>Oprya</last_name>
	<last_name>Oshchypko</last_name>
	<last_name>Ostapenko</last_name>
	<last_name>Panas</last_name>
	<last_name>Panin</last_name>
	<last_name>Parfenov</last_name>
	<last_name>Pashaiv</last_name>
	<last_name>Pasulko</last_name>
	<last_name>Patyak</last_name>
	<last_name>Pavlenko</last_name>
	<last_name>Pavlov</last_name>
	<last_name>Perepadenko</last_name>
	<last_name>Perkhun</last_name>
	<last_name>Peskov</last_name>
	<last_name>Petrivskiy</last_name>
	<last_name>Pikhur</last_name>
	<last_name>Pilipchuk</last_name>
	<last_name>Pisanjuk</last_name>
	<last_name>Pivnenko</last_name>
	<last_name>Platon</last_name>
	<last_name>Pohorilyy</last_name>
	<last_name>Pokarynin</last_name>
	<last_name>Pokhlebaev</last_name>
	<last_name>Polovkov</last_name>
	<last_name>Poltavets</last_name>
	<last_name>Polyansky</last_name>
	<last_name>Polytilo</last_name>
	<last_name>Pomazun</last_name>
	<last_name>Ponomarev</last_name>
	<last_name>Popov</last_name>
	<last_name>Porkujan</last_name>
	<last_name>Postransky</last_name>
	<last_name>Postupalenko</last_name>
	<last_name>Predko</last_name>
	<last_name>Priyomov</last_name>
	<last_name>Prokopenko</last_name>
	<last_name>Protasov</last_name>
	<last_name>Protsyuk</last_name>
	<last_name>Pryvma</last_name>
	<last_name>Pshenychnykh</last_name>
	<last_name>Ptachyk</last_name>
	<last_name>Pyatov</last_name>
	<last_name>Rad</last_name>
	<last_name>Radchenko</last_name>
	<last_name>Raspopov</last_name>
	<last_name>Rats</last_name>
	<last_name>Rebenok</last_name>
	<last_name>Rebrov</last_name>
	<last_name>Reshko</last_name>
	<last_name>Reva</last_name>
	<last_name>Riabyy</last_name>
	<last_name>Rodevych</last_name>
	<last_name>Romanchuk</last_name>
	<last_name>Romanenko</last_name>
	<last_name>Romaniuk</last_name>
	<last_name>Rotan</last_name>
	<last_name>Rozgon</last_name>
	<last_name>Roziznanyy</last_name>
	<last_name>Rudakov</last_name>
	<last_name>Rudenko</last_name>
	<last_name>Rusol</last_name>
	<last_name>Rybalka</last_name>
	<last_name>Rybka</last_name>
	<last_name>Rykun</last_name>
	<last_name>Sabo</last_name>
	<last_name>Sachko</last_name>
	<last_name>Sahaydak</last_name>
	<last_name>Sakhnyuk</last_name>
	<last_name>Salenko</last_name>
	<last_name>Samborskyi</last_name>
	<last_name>Santrapinskykh</last_name>
	<last_name>Sapay</last_name>
	<last_name>Savin</last_name>
	<last_name>Seleznyov</last_name>
	<last_name>Selin</last_name>
	<last_name>Semenko</last_name>
	<last_name>Semochko</last_name>
	<last_name>Serdyuk</last_name>
	<last_name>Serebrennikov</last_name>
	<last_name>Serebryanikov</last_name>
	<last_name>Sernecki</last_name>
	<last_name>Shakhov</last_name>
	<last_name>Shandruk</last_name>
	<last_name>Shapovalov</last_name>
	<last_name>Sharan</last_name>
	<last_name>Shatalov</last_name>
	<last_name>Shcherbakov</last_name>
	<last_name>Shelayev</last_name>
	<last_name>Shelikhov</last_name>
	<last_name>Shepytskyy</last_name>
	<last_name>Shershun</last_name>
	<last_name>Shevchenko</last_name>
	<last_name>Shevchuk</last_name>
	<last_name>Shevelyukhin</last_name>
	<last_name>Shiryayev</last_name>
	<last_name>Shmakov</last_name>
	<last_name>Shmatovalenko</last_name>
	<last_name>Shopin</last_name>
	<last_name>Shovkovskiy</last_name>
	<last_name>Shpak</last_name>
	<last_name>Shpuk</last_name>
	<last_name>Shukhovtsev</last_name>
	<last_name>Shumeiko</last_name>
	<last_name>Shust</last_name>
	<last_name>Shutkov</last_name>
	<last_name>Shynder</last_name>
	<last_name>Shyschenko</last_name>
	<last_name>Sidelnikov</last_name>
	<last_name>Silyuk</last_name>
	<last_name>Siminin</last_name>
	<last_name>Siryk</last_name>
	<last_name>Skachenko</last_name>
	<last_name>Skepsky</last_name>
	<last_name>Skoba</last_name>
	<last_name>Skrypnyk</last_name>
	<last_name>Sloboda</last_name>
	<last_name>Slyusar</last_name>
	<last_name>Smalyukh</last_name>
	<last_name>Smirnov</last_name>
	<last_name>Snytko</last_name>
	<last_name>Sokolenko</last_name>
	<last_name>Sokolovsky</last_name>
	<last_name>Solyanyk</last_name>
	<last_name>Sosnikhin</last_name>
	<last_name>Spivak</last_name>
	<last_name>Stargorodsky</last_name>
	<last_name>Starostiak</last_name>
	<last_name>Startsev</last_name>
	<last_name>Stepanenko</last_name>
	<last_name>Stepanov</last_name>
	<last_name>Stoyan</last_name>
	<last_name>Stoyko</last_name>
	<last_name>Subochev</last_name>
	<last_name>Sukhotskyy</last_name>
	<last_name>Susloparov</last_name>
	<last_name>Sviderskiy</last_name>
	<last_name>Svorak</last_name>
	<last_name>Sykorskyy</last_name>
	<last_name>Symonenko</last_name>
	<last_name>Sytnyk</last_name>
	<last_name>Taran</last_name>
	<last_name>Tarasenko</last_name>
	<last_name>Tarhanchuk</last_name>
	<last_name>Teplyy</last_name>
	<last_name>Tistyk</last_name>
	<last_name>Tkachenko</last_name>
	<last_name>Tkachuk</last_name>
	<last_name>Tkatchuk</last_name>
	<last_name>Tlumak</last_name>
	<last_name>Tovt</last_name>
	<last_name>Troshkin</last_name>
	<last_name>Trusevich</last_name>
	<last_name>Trusevych</last_name>
	<last_name>Tselikh</last_name>
	<last_name>Tsimakuridze</last_name>
	<last_name>Tsveiba</last_name>
	<last_name>Tsygan</last_name>
	<last_name>Tsymbalar</last_name>
	<last_name>Turchaniv</last_name>
	<last_name>Tymchenko</last_name>
	<last_name>Tymoshchuk</last_name>
	<last_name>Tyshchenko</last_name>
	<last_name>Ussoltsev</last_name>
	<last_name>Valeyev</last_name>
	<last_name>Valyayev</last_name>
	<last_name>Vartsaba</last_name>
	<last_name>Vashchuk</last_name>
	<last_name>Vasyn</last_name>
	<last_name>Velychko</last_name>
	<last_name>Venglinsky</last_name>
	<last_name>Vernydub</last_name>
	<last_name>Virt</last_name>
	<last_name>Vishnevsky</last_name>
	<last_name>Vitoshynskyi</last_name>
	<last_name>Vladov</last_name>
	<last_name>Vlasenko</last_name>
	<last_name>Voinov</last_name>
	<last_name>Voloshyn</last_name>
	<last_name>Volovyk</last_name>
	<last_name>Vorobei</last_name>
	<last_name>Vorobey</last_name>
	<last_name>Vorobeyev</last_name>
	<last_name>Voronin</last_name>
	<last_name>Vovkodav</last_name>
	<last_name>Vyshnyak</last_name>
	<last_name>Vysotskyy</last_name>
	<last_name>Yakovenko</last_name>
	<last_name>Yaremchuk</last_name>
	<last_name>Yarmash</last_name>
	<last_name>Yarmolenko</last_name>
	<last_name>Yaroshenko</last_name>
	<last_name>Yaschenko</last_name>
	<last_name>Yashkin</last_name>
	<last_name>Yatsenko</last_name>
	<last_name>Yesin</last_name>
	<last_name>Yesyp</last_name>
	<last_name>Yevseyev</last_name>
	<last_name>Yevtushenko</last_name>
	<last_name>Yevtushok</last_name>
	<last_name>Yezerskiy</last_name>
	<last_name>Yuran</last_name>
	<last_name>Yurchyshyn</last_name>
	<last_name>Zakarlyuka</last_name>
	<last_name>Zakharevych</last_name>
	<last_name>Zavarov</last_name>
	<last_name>Zaychuk</last_name>
	<last_name>Zaynchkovskyy</last_name>
	<last_name>Zborovskyy</last_name>
	<last_name>Zeldi</last_name>
	<last_name>Zhdankov</last_name>
	<last_name>Zhenyukh</last_name>
	<last_name>Zherzh</last_name>
	<last_name>Zhuravliov</last_name>
	<last_name>Zinchenko</last_name>
	<last_name>Zorya</last_name>
	<last_name>Zotov</last_name>
	<last_name>Zozulya</last_name>
	<last_name>Zubov</last_name>
	<last_name>Zuyev</last_name>
</names>