<?xml version="1.0" encoding="UTF-8"?>
<country>
  <name>Austria</name>
  <rating>8</rating>
  <symbol>flag_austria.png</symbol>
  <sid>germany</sid>

  <leagues>
    <league>austria1</league>
    <league>austria2</league>
    <league>austria3a</league>
    <league>austria3b</league>
    <league>austria3c</league>
  </leagues>

  <cups>
    <cup>austria_cup</cup>
    <cup>europe_uefa</cup>
    <cup>europe_cwc</cup>
    <cup>europe_champ_league</cup>
    <cup>supercup_europe_uefa</cup>
    <cup>supercup_europe_intercontinental</cup>
  </cups>

</country>
