<?xml version="1.0" encoding="UTF-8"?>
<cup>
  <name>Puchar Polski</name>
  <symbol>flag_poland.png</symbol>
  <sid>poland_puchar</sid>
  <last_week>41</last_week>
  <week_gap>3</week_gap>
  <property>national</property>

  <cup_rounds>
    <cup_round>
      <home_away>0</home_away>
      <choose_teams>
	<choose_team>
	  <choose_team_sid>poland3a</choose_team_sid>
	</choose_team>
	<choose_team>
	  <choose_team_sid>poland3b</choose_team_sid>
	</choose_team>
	<choose_team>
	  <choose_team_sid>poland3c</choose_team_sid>
	</choose_team>
	<choose_team>
	  <choose_team_sid>poland3d</choose_team_sid>
	</choose_team>
        <choose_team>
	  <choose_team_sid>poland2</choose_team_sid>
        </choose_team>
      </choose_teams>
    </cup_round>

    <cup_round>
      <home_away>0</home_away>
    </cup_round>
    
    <cup_round>
    </cup_round>

    <cup_round>
      <choose_team>
	  <choose_team_sid>poland1</choose_team_sid>
      </choose_team>
    </cup_round>
    
    <cup_round>
    </cup_round>
    
    <cup_round>
    </cup_round>
    
    <cup_round>
    </cup_round>
    
    <cup_round>
    </cup_round>

  </cup_rounds>
</cup>
